sastadev/ASTApostfunctions.py
sastadev/CHAT_Annotation.py
sastadev/NLtypes.py
sastadev/SAFreader.py
sastadev/SRFreader.py
sastadev/STAPpostfunctions.py
sastadev/Sziplus.py
sastadev/TARSPpostfunctions.py
sastadev/TARSPscreening.py
sastadev/V2violations.py
sastadev/__init__.py
sastadev/__main__.py
sastadev/adapt_pt.py
sastadev/addsamplecol.py
sastadev/adhocworkfile.py
sastadev/advpsplit.py
sastadev/allresults.py
sastadev/alpino.py
sastadev/alpinocompound.py
sastadev/alpinoparsing.py
sastadev/anonymization.py
sastadev/apostroftest.py
sastadev/asta_neo.py
sastadev/asta_queries.py
sastadev/astaforms.py
sastadev/auchannsettings.py
sastadev/basicreplacements.py
sastadev/celex_subclasses.py
sastadev/celexlexicon.py
sastadev/chatundo.py
sastadev/checkcorrection.py
sastadev/childesspellingcorrector.py
sastadev/cleanCHILDEStokens.py
sastadev/code_frequencies.py
sastadev/commarepetition.py
sastadev/compounds.py
sastadev/conf.py
sastadev/constants.py
sastadev/context.py
sastadev/correct_tr_verbs.py
sastadev/correctionexample.py
sastadev/correctionlabels.py
sastadev/correctionparameters.py
sastadev/corrector.py
sastadev/correcttreebank.py
sastadev/counterfunctions.py
sastadev/datasets.py
sastadev/dcoi.py
sastadev/dedup.py
sastadev/deregularise.py
sastadev/develop.py
sastadev/displaytree.py
sastadev/dropfinalvowel.py
sastadev/eenbeetje.py
sastadev/exampletrees.py
sastadev/expandquery.py
sastadev/external_functions.py
sastadev/filefunctions.py
sastadev/find_ngram.py
sastadev/forms.py
sastadev/fuzzyrepetition.py
sastadev/generatemacros.py
sastadev/gigant_molex_tsv.py
sastadev/goldcountreader.py
sastadev/grammarerrors.py
sastadev/history.py
sastadev/iedims.py
sastadev/imperatives.py
sastadev/imply.py
sastadev/interruptedutterances.py
sastadev/lexicon.py
sastadev/longqueries.py
sastadev/macrolength.py
sastadev/macros.py
sastadev/memoize.py
sastadev/metadata.py
sastadev/methodinfo.py
sastadev/methods.py
sastadev/mismatches.py
sastadev/mksilver.py
sastadev/moregrammarerrors.py
sastadev-0.4.1.dist-info/licenses/LICENSE
sastadev-0.4.1.dist-info/METADATA
sastadev-0.4.1.dist-info/WHEEL
sastadev-0.4.1.dist-info/entry_points.txt
sastadev-0.4.1.dist-info/top_level.txt
sastadev-0.4.1.dist-info/RECORD
