Metadata-Version: 2.4
Name: sastadev
Version: 0.4.1
Summary: Linguistic functions for SASTA tool
Home-page: https://github.com/UUDigitalHumanitieslab/sastadev
Author: Research Software Lab - Centre for Digital Humanities - Utrecht University
Author-email: digitalhumanities@uu.nl
License: BSD-3-Clause
Requires-Python: >=3.7, <4
License-File: LICENSE
Requires-Dist: auchann
Requires-Dist: lxml
Requires-Dist: openpyxl
Requires-Dist: XlsxWriter
Requires-Dist: typing-extensions
Requires-Dist: pyspellchecker
Requires-Dist: more-itertools
Dynamic: author
Dynamic: author-email
Dynamic: description
Dynamic: description-content-type
Dynamic: home-page
Dynamic: license
Dynamic: license-file
Dynamic: requires-dist
Dynamic: requires-python
Dynamic: summary
